argscheck/__init__.py
argscheck/collection.py
argscheck/comparable.py
argscheck/core.py
argscheck/iter.py
argscheck/numeric.py
argscheck/optional.py
argscheck/pathlike.py
argscheck/sequence.py
argscheck/string.py
argscheck/utils.py
argscheck-2.0.0.dist-info/LICENSE
argscheck-2.0.0.dist-info/METADATA
argscheck-2.0.0.dist-info/WHEEL
argscheck-2.0.0.dist-info/top_level.txt
argscheck-2.0.0.dist-info/RECORD
