Metadata-Version: 2.1
Name: argscheck
Version: 2.0.0
Summary: Effortless Argument Checking For Python
Home-page: https://github.com/artiumd/argscheck
Author: Artium Dashuta
Author-email: artium89@gmail.com
License: UNKNOWN
Project-URL: Bug Tracker, https://github.com/artiumd/argscheck/issues
Platform: UNKNOWN
Classifier: Programming Language :: Python :: 3
Classifier: License :: OSI Approved :: MIT License
Classifier: Operating System :: OS Independent
Requires-Python: >=3.6
License-File: LICENSE
